[
  {
    "id": "act-001",
    "title": "Community Meetup: Intro to Quantum Computing",
    "date": "2025-10-20",
    "description": "A friendly meetup introducing the basics of quantum computing. Beginners welcome — light refreshments provided."
  },
  {
    "id": "act-002",
    "title": "Women in Tech Panel",
    "date": "2025-11-05",
    "description": "Panel discussion with women leaders from academia and industry about careers, mentorship, and inclusion."
  },
  {
    "id": "act-003",
    "title": "Hands-on Workshop: Quantum Circuits",
    "date": "2025-11-15",
    "description": "Practical lab where attendees will build and simulate simple quantum circuits on cloud providers."
  },
  {
    "id": "act-004",
    "title": "Online Webinar: Quantum Algorithms Overview",
    "date": "2025-12-01",
    "description": "Join us online for an accessible overview of quantum algorithms and their potential applications."
  },
  {
    "id": "act-005",
    "title": "Networking Night — Startups & Founders",
    "date": "2025-10-28",
    "description": "An evening for founders, investors and startup enthusiasts to connect and share opportunities."
  },
  {
    "id": "act-006",
    "title": "Student Poster Session",
    "date": "2025-10-12",
    "description": "Undergraduate and graduate students present research posters. Open to the public."
  },
  {
    "id": "act-007",
    "title": "Hackathon: Quantum Challenge (48h)",
    "date": "2026-01-09",
    "description": "A 48-hour hackathon focused on building useful tools and demos for quantum software. Teams of up to 4."
  },
  {
    "id": "act-008",
    "title": "Coffee & Code — Study Group",
    "date": "2025-10-08",
    "description": "Casual study group for people learning quantum programming. Bring your laptop and questions."
  },
  {
    "id": "act-009",
    "title": "Lecture: Quantum Error Correction",
    "date": "2025-11-22",
    "description": "An advanced lecture on quantum error correction techniques and their implementations."
  },
  {
    "id": "act-010",
    "title": "Community Volunteer Day",
    "date": "2025-10-18",
    "description": "Help us prepare event spaces and materials. No experience required — coffee provided."
  },
  {
    "id": "act-011",
    "title": "Mentorship Office Hours",
    "date": "2025-10-25",
    "description": "Sign up for 20-minute mentorship slots with experienced industry professionals."
  },
  {
    "id": "act-012",
    "title": "End-of-Year Social",
    "date": "2025-12-20",
    "description": "Celebrate the year's achievements with drinks, awards, and music. Tickets required."
  }
]